odoo/addons/contract_forecast_brand/README.rst
odoo/addons/contract_forecast_brand/__init__.py
odoo/addons/contract_forecast_brand/__manifest__.py
odoo/addons/contract_forecast_brand/hooks.py
odoo/addons/contract_forecast_brand/i18n/contract_forecast_brand.pot
odoo/addons/contract_forecast_brand/models/__init__.py
odoo/addons/contract_forecast_brand/models/contract_contract.py
odoo/addons/contract_forecast_brand/models/contract_line.py
odoo/addons/contract_forecast_brand/models/contract_line_forecast_period.py
odoo/addons/contract_forecast_brand/readme/CONTRIBUTORS.rst
odoo/addons/contract_forecast_brand/readme/DESCRIPTION.rst
odoo/addons/contract_forecast_brand/static/description/icon.png
odoo/addons/contract_forecast_brand/static/description/index.html
odoo/addons/contract_forecast_brand/tests/__init__.py
odoo/addons/contract_forecast_brand/tests/test_contract.py
odoo12_addon_contract_forecast_brand-12.0.1.0.1.dist-info/METADATA
odoo12_addon_contract_forecast_brand-12.0.1.0.1.dist-info/WHEEL
odoo12_addon_contract_forecast_brand-12.0.1.0.1.dist-info/top_level.txt
odoo12_addon_contract_forecast_brand-12.0.1.0.1.dist-info/RECORD
