Metadata-Version: 2.1
Name: odoo12-addon-contract-forecast-brand
Version: 12.0.1.0.1
Summary: This addon add brand field for contract forecast
Home-page: https://github.com/OCA/brand
Author: ACSONE SA/NV,Odoo Community Association (OCA)
Author-email: support@odoo-community.org
License: AGPL-3
Platform: UNKNOWN
Classifier: Programming Language :: Python
Classifier: Framework :: Odoo
Classifier: License :: OSI Approved :: GNU Affero General Public License v3
Requires-Python: >=3.5
Requires-Dist: odoo12-addon-contract-brand
Requires-Dist: odoo12-addon-contract-forecast
Requires-Dist: odoo (<12.1dev,>=12.0a)
